cookiecutter.json
cookiecutter_poetry/__init__.py
cookiecutter_poetry/cli.py
hooks/post_gen_project.py
hooks/pre_gen_project.py
{{cookiecutter.project_name}}/.devcontainer/devcontainer.json
{{cookiecutter.project_name}}/.devcontainer/postCreateCommand.sh
{{cookiecutter.project_name}}/.editorconfig
{{cookiecutter.project_name}}/.github/actions/setup-poetry-env/action.yml
{{cookiecutter.project_name}}/.github/workflows/build-and-deploy.yml
{{cookiecutter.project_name}}/.github/workflows/deploy-docs.yml
{{cookiecutter.project_name}}/.github/workflows/publish-package.yml
{{cookiecutter.project_name}}/.github/workflows/test-check-build.yml
{{cookiecutter.project_name}}/.github/workflows/version-bump-and-release.yml
{{cookiecutter.project_name}}/.gitignore
{{cookiecutter.project_name}}/.pre-commit-config.yaml
{{cookiecutter.project_name}}/.vscode/launch.json
{{cookiecutter.project_name}}/.vscode/settings.json
{{cookiecutter.project_name}}/Dockerfile
{{cookiecutter.project_name}}/LICENSE
{{cookiecutter.project_name}}/Makefile
{{cookiecutter.project_name}}/README.md
{{cookiecutter.project_name}}/artifacts/documents/.gitkeep
{{cookiecutter.project_name}}/artifacts/processed/.gitkeep
{{cookiecutter.project_name}}/codecov.yaml
{{cookiecutter.project_name}}/docker-compose.yml
{{cookiecutter.project_name}}/docs/assets/favicon.ico
{{cookiecutter.project_name}}/docs/assets/logo.png
{{cookiecutter.project_name}}/docs/index.md
{{cookiecutter.project_name}}/docs/modules.md
{{cookiecutter.project_name}}/mkdocs.yml
{{cookiecutter.project_name}}/notebooks/trails.ipynb
{{cookiecutter.project_name}}/poetry.toml
{{cookiecutter.project_name}}/pyproject.toml
{{cookiecutter.project_name}}/tests/test_api_endpoint.py
{{cookiecutter.project_name}}/tox.ini
{{cookiecutter.project_name}}/{{cookiecutter.project_slug}}/__init__.py
{{cookiecutter.project_name}}/{{cookiecutter.project_slug}}/api/__init__.py
{{cookiecutter.project_name}}/{{cookiecutter.project_slug}}/api/endpoint.py
cookiecutter_rag-0.0.3.dist-info/LICENSE
cookiecutter_rag-0.0.3.dist-info/METADATA
cookiecutter_rag-0.0.3.dist-info/WHEEL
cookiecutter_rag-0.0.3.dist-info/entry_points.txt
cookiecutter_rag-0.0.3.dist-info/RECORD
